open_python_skills/__init__.py
open_python_skills/cli.py
open_python_skills/commit-message/SKILL.md
open_python_skills/commit-message/data/commit_patterns.json
open_python_skills/commit-message/scripts/analyze_changes.py
open_python_skills/excalidraw-ai/SKILL.md
open_python_skills/excalidraw-ai/assets/aws-architecture-icons.excalidrawlib
open_python_skills/excalidraw-ai/assets/drwnio.excalidrawlib
open_python_skills/excalidraw-ai/assets/software-architecture.excalidrawlib
open_python_skills/excalidraw-ai/assets/system-design-template.excalidrawlib
open_python_skills/excalidraw-ai/assets/system-design.excalidrawlib
open_python_skills/python-backend/SKILL.md
open_python_skills/python-backend/references/database_patterns.md
open_python_skills/python-backend/references/fastapi_patterns.md
open_python_skills/python-backend/references/security_patterns.md
open_python_skills/python-backend/references/upstash_patterns.md
open_python_skills/ty-skills/SKILL.md
open_python_skills/ty-skills/references/advanced_patterns.md
open_python_skills/ty-skills/references/common_errors.md
open_python_skills/ty-skills/references/migration_guide.md
open_python_skills/ty-skills/references/ty_rules_reference.md
open_python_skills/ty-skills/references/typing_cheatsheet.md
open_python_skills/ty-skills/references/editor_setup/cursor.md
open_python_skills/ty-skills/references/editor_setup/neovim.md
open_python_skills/ty-skills/references/editor_setup/vscode.md
open_python_skills-0.1.5.dist-info/METADATA
open_python_skills-0.1.5.dist-info/WHEEL
open_python_skills-0.1.5.dist-info/entry_points.txt
open_python_skills-0.1.5.dist-info/licenses/LICENSE
open_python_skills-0.1.5.dist-info/RECORD
