Metadata-Version: 2.4
Name: open-python-skills
Version: 0.1.5
Summary: AI skill for Python backend development - FastAPI, SQLAlchemy, Redis, security patterns
Project-URL: Homepage, https://github.com/henryperkins/open-python-skills
Project-URL: Repository, https://github.com/henryperkins/open-python-skills
Project-URL: Documentation, https://github.com/henryperkins/open-python-skills#readme
Project-URL: Issues, https://github.com/henryperkins/open-python-skills/issues
Author-email: Haoxiang Jia <henry@podpitch.com>
License: MIT
License-File: LICENSE
Keywords: ai-assistant,backend,claude,cli,copilot,cursor,fastapi,python,redis,skills,sqlalchemy,upstash,windsurf
Classifier: Development Status :: 4 - Beta
Classifier: Environment :: Console
Classifier: Intended Audience :: Developers
Classifier: License :: OSI Approved :: MIT License
Classifier: Programming Language :: Python :: 3
Classifier: Programming Language :: Python :: 3.8
Classifier: Programming Language :: Python :: 3.9
Classifier: Programming Language :: Python :: 3.10
Classifier: Programming Language :: Python :: 3.11
Classifier: Programming Language :: Python :: 3.12
Classifier: Programming Language :: Python :: 3.13
Classifier: Topic :: Software Development :: Code Generators
Classifier: Topic :: Software Development :: Libraries :: Python Modules
Requires-Python: >=3.8
